[
	{
		"__TYPE__": "SharedSliceContent",
		"variation": "default",
		"primary": {
			"background_color": {
				"__TYPE__": "FieldContent",
				"value": "Default",
				"type": "Select"
			},
			"title": {
				"__TYPE__": "StructuredTextContent",
				"value": [
					{
						"type": "paragraph",
						"content": {
							"text": "Ad et et eu anim cillum. Occaecat Lorem eu non."
						}
					}
				]
			},
			"body": {
				"__TYPE__": "StructuredTextContent",
				"value": [
					{
						"type": "paragraph",
						"content": {
							"text": "Do nostrud qui cillum cupidatat et duis cupidatat."
						}
					}
				]
			},
			"buttons": {
				"__TYPE__": "RepeatableContent",
				"type": "Link",
				"value": [
					{
						"key": "05b9f049-7872-4b45-8bef-a046c0594d6e",
						"__TYPE__": "LinkContent",
						"value": {
							"__TYPE__": "ExternalLink",
							"url": "http://google.com",
							"text": "bright"
						}
					}
				]
			},
			"accordion": {
				"__TYPE__": "GroupContentType",
				"value": [
					{
						"__TYPE__": "GroupItemContent",
						"value": [
							[
								"icon",
								{
									"origin": {
										"id": "main",
										"url": "https://images.unsplash.com/photo-1541807084-5c52b6b3adef",
										"width": 4000,
										"height": 6000
									},
									"url": "https://images.unsplash.com/photo-1541807084-5c52b6b3adef",
									"width": 4000,
									"height": 6000,
									"edit": {
										"zoom": 1,
										"crop": {
											"x": 0,
											"y": 0
										},
										"background": "transparent"
									},
									"alt": "separate",
									"credits": null,
									"__TYPE__": "ImageContent",
									"thumbnails": {}
								}
							],
							[
								"title",
								{
									"__TYPE__": "StructuredTextContent",
									"value": [
										{
											"type": "paragraph",
											"content": {
												"text": "Eiusmod sit enim elit. Elit voluptate irure sint anim pariatur excepteur esse ad nulla. Anim voluptate amet occaecat fugiat laboris eu excepteur dolor labore."
											}
										}
									]
								}
							],
							[
								"body",
								{
									"__TYPE__": "StructuredTextContent",
									"value": [
										{
											"type": "paragraph",
											"content": {
												"text": "Veniam tempor in ut consectetur nostrud id laboris non est eiusmod occaecat."
											}
										}
									]
								}
							],
							[
								"button",
								{
									"__TYPE__": "LinkContent",
									"key": "dee824fc-eae4-478e-bfe3-81a32ac13568",
									"value": {
										"__TYPE__": "ExternalLink",
										"url": "https://prismic.io",
										"text": "paint"
									}
								}
							]
						]
					}
				]
			}
		},
		"items": []
	}
]